{
 "attach_files": "",
 "attach_print": 0,
 "channel": "System Notification",
 "condition_type": "Filters",
 "creation": "2025-12-08 16:35:14.874873",
 "days_in_advance": 0,
 "docstatus": 0,
 "doctype": "Notification",
 "document_type": "Issue Report",
 "enabled": 1,
 "event": "New",
 "filters": "[]",
 "idx": 0,
 "is_standard": 1,
 "message": "<p>Add your message here</p>\n",
 "message_type": "Markdown",
 "minutes_offset": 0,
 "modified": "2025-12-11 11:06:36.774897",
 "modified_by": "Administrator",
 "module": "Neighborhood Watch",
 "name": "New Issue",
 "owner": "Administrator",
 "recipients": [
  {
   "receiver_by_role": "Admin"
  }
 ],
 "send_system_notification": 0,
 "send_to_all_assignees": 0,
 "subject": "{{doc.resident}} Has Arised An Issue",
 "value_changed": "status"
}
